LICENSE-MIT
MANIFEST.in
README.rst
setup.py
shinto/__init__.py
shinto.egg-info/PKG-INFO
shinto.egg-info/SOURCES.txt
shinto.egg-info/dependency_links.txt
shinto.egg-info/top_level.txt
tests/__init__.py